memtop/__init__.py
memtop-1.0.4.data/scripts/memtop
memtop-1.0.4.dist-info/METADATA
memtop-1.0.4.dist-info/RECORD
memtop-1.0.4.dist-info/WHEEL
memtop-1.0.4.dist-info/top_level.txt
