Metadata-Version: 2.1
Name: memtop
Version: 1.0.4
Summary: view memory consumption of processes
Home-page: https://github.com/MartinThoma/memtop
Author: Tibor Bamhor, Martin Thoma
Author-email: info@martin-thoma.de
Maintainer: Martin Thoma
Maintainer-email: info@martin-thoma.de
License: GPLv2
Download-URL: https://github.com/MartinThoma/memtop
Keywords: memory,consumption
Platform: Linux
Platform: MacOS X
Classifier: Development Status :: 7 - Inactive
Classifier: Environment :: Console
Classifier: Intended Audience :: Developers
Classifier: License :: OSI Approved :: GNU General Public License (GPL)
Classifier: Natural Language :: English
Classifier: Programming Language :: Python :: 2.7
Classifier: Programming Language :: Python :: 3
Classifier: Programming Language :: Python :: 3.3
Classifier: Programming Language :: Python :: 3.4
Classifier: Topic :: Software Development
Classifier: Topic :: Utilities
Requires-Dist: argparse
